ark/__init__.py
ark/_base_client.py
ark/_client.py
ark/_compat.py
ark/_constants.py
ark/_exceptions.py
ark/_files.py
ark/_models.py
ark/_qs.py
ark/_resource.py
ark/_response.py
ark/_streaming.py
ark/_types.py
ark/_version.py
ark/pagination.py
ark/py.typed
ark/_utils/__init__.py
ark/_utils/_compat.py
ark/_utils/_datetime_parse.py
ark/_utils/_json.py
ark/_utils/_logs.py
ark/_utils/_proxy.py
ark/_utils/_reflection.py
ark/_utils/_resources_proxy.py
ark/_utils/_streams.py
ark/_utils/_sync.py
ark/_utils/_transform.py
ark/_utils/_typing.py
ark/_utils/_utils.py
ark/lib/.keep
ark/resources/__init__.py
ark/resources/domains.py
ark/resources/emails.py
ark/resources/logs.py
ark/resources/suppressions.py
ark/resources/tracking.py
ark/resources/usage.py
ark/resources/webhooks.py
ark/types/__init__.py
ark/types/dns_record.py
ark/types/domain_create_params.py
ark/types/domain_create_response.py
ark/types/domain_delete_response.py
ark/types/domain_list_response.py
ark/types/domain_retrieve_response.py
ark/types/domain_verify_response.py
ark/types/email_list_params.py
ark/types/email_list_response.py
ark/types/email_retrieve_deliveries_response.py
ark/types/email_retrieve_params.py
ark/types/email_retrieve_response.py
ark/types/email_retry_response.py
ark/types/email_send_batch_params.py
ark/types/email_send_batch_response.py
ark/types/email_send_params.py
ark/types/email_send_raw_params.py
ark/types/email_send_raw_response.py
ark/types/email_send_response.py
ark/types/log_entry.py
ark/types/log_entry_detail.py
ark/types/log_list_params.py
ark/types/log_retrieve_response.py
ark/types/suppression_bulk_create_params.py
ark/types/suppression_bulk_create_response.py
ark/types/suppression_create_params.py
ark/types/suppression_create_response.py
ark/types/suppression_delete_response.py
ark/types/suppression_list_params.py
ark/types/suppression_list_response.py
ark/types/suppression_retrieve_response.py
ark/types/track_domain.py
ark/types/tracking_create_params.py
ark_email-0.16.0.dist-info/METADATA
ark_email-0.16.0.dist-info/WHEEL
ark_email-0.16.0.dist-info/licenses/LICENSE
ark_email-0.16.0.dist-info/RECORD
